spyll/__init__.py
spyll/spyll.py
spyll-1.2.3.dist-info/LICENSE
spyll-1.2.3.dist-info/METADATA
spyll-1.2.3.dist-info/WHEEL
spyll-1.2.3.dist-info/top_level.txt
spyll-1.2.3.dist-info/RECORD
