Metadata-Version: 2.1
Name: spyll
Version: 1.2.3
Summary: Spyll is an open source Python package that aims to make text file handling more streamlined. Works with Python versions 3.6+
Home-page: https://dangolabs.com
Author: Dango Labs
Author-email: info@dangolabs.com
Classifier: Programming Language :: Python :: 3
Classifier: License :: OSI Approved :: MIT License
Classifier: Operating System :: OS Independent
License-File: LICENSE
